Metadata-Version: 2.4
Name: guardefi
Version: 1.0.0
Summary: World's Strongest Smart Contract Security Scanner with Machine Learning
Home-page: https://github.com/scorpius-security/scorpius
Author: Scorpius Security Team
Author-email: Scorpius Security Team <security@scorpius.io>
Maintainer-email: Scorpius Security Team <security@scorpius.io>
License: MIT
Project-URL: Homepage, https://github.com/scorpius-security/scorpius
Project-URL: Documentation, https://docs.scorpius.io
Project-URL: Repository, https://github.com/scorpius-security/scorpius
Project-URL: Bug Reports, https://github.com/scorpius-security/scorpius/issues
Project-URL: Changelog, https://github.com/scorpius-security/scorpius/blob/main/CHANGELOG.md
Keywords: smart-contract,security,vulnerability,scanner,blockchain,ethereum,solidity,defi,audit,machine-learning,ai
Classifier: Development Status :: 5 - Production/Stable
Classifier: Intended Audience :: Developers
Classifier: Intended Audience :: Information Technology
Classifier: Topic :: Security
Classifier: Topic :: Software Development :: Quality Assurance
Classifier: Topic :: Software Development :: Testing
Classifier: License :: OSI Approved :: MIT License
Classifier: Programming Language :: Python :: 3
Classifier: Programming Language :: Python :: 3.8
Classifier: Programming Language :: Python :: 3.9
Classifier: Programming Language :: Python :: 3.10
Classifier: Programming Language :: Python :: 3.11
Classifier: Programming Language :: Python :: 3.12
Classifier: Operating System :: OS Independent
Classifier: Environment :: Console
Classifier: Natural Language :: English
Requires-Python: >=3.8
License-File: LICENSE
Requires-Dist: click>=8.0.0
Requires-Dist: rich>=13.0.0
Requires-Dist: pandas>=1.5.0
Requires-Dist: numpy>=1.20.0
Requires-Dist: scikit-learn>=1.0.0
Requires-Dist: aiohttp>=3.8.0
Requires-Dist: beautifulsoup4>=4.11.0
Requires-Dist: lxml>=4.9.0
Requires-Dist: python-dateutil>=2.8.0
Requires-Dist: tldextract>=3.4.0
Requires-Dist: pydantic>=1.10.0
Provides-Extra: api
Requires-Dist: fastapi>=0.100.0; extra == "api"
Requires-Dist: uvicorn[standard]>=0.20.0; extra == "api"
Provides-Extra: pdf
Requires-Dist: reportlab>=4.0.0; extra == "pdf"
Requires-Dist: pypdf>=3.0.0; extra == "pdf"
Provides-Extra: dev
Requires-Dist: pytest>=7.0.0; extra == "dev"
Requires-Dist: pytest-asyncio>=0.21.0; extra == "dev"
Requires-Dist: pytest-cov>=4.0.0; extra == "dev"
Requires-Dist: black>=22.0.0; extra == "dev"
Requires-Dist: ruff>=0.1.0; extra == "dev"
Requires-Dist: mypy>=1.0.0; extra == "dev"
Provides-Extra: enterprise
Requires-Dist: redis>=4.0.0; extra == "enterprise"
Requires-Dist: celery>=5.0.0; extra == "enterprise"
Requires-Dist: prometheus-client>=0.15.0; extra == "enterprise"
Provides-Extra: all
Requires-Dist: fastapi>=0.100.0; extra == "all"
Requires-Dist: uvicorn[standard]>=0.20.0; extra == "all"
Requires-Dist: reportlab>=4.0.0; extra == "all"
Requires-Dist: pypdf>=3.0.0; extra == "all"
Requires-Dist: redis>=4.0.0; extra == "all"
Requires-Dist: celery>=5.0.0; extra == "all"
Requires-Dist: prometheus-client>=0.15.0; extra == "all"
Dynamic: author
Dynamic: home-page
Dynamic: license-file
Dynamic: requires-python
